testgres/operations/exceptions.py
testgres/operations/helpers.py
testgres/operations/local_ops.py
testgres/operations/os_ops.py
testgres/operations/raise_error.py
testgres/operations/remote_ops.py
testgres_os_ops-1.1.0.dist-info/licenses/LICENSE
testgres_os_ops-1.1.0.dist-info/METADATA
testgres_os_ops-1.1.0.dist-info/WHEEL
testgres_os_ops-1.1.0.dist-info/top_level.txt
testgres_os_ops-1.1.0.dist-info/RECORD
