Metadata-Version: 2.4
Name: testgres.os_ops
Version: 1.1.0
Summary: Testgres subsystem to work with OS
Author-email: Postgres Professional <testgres@postgrespro.ru>
License: PostgreSQL
Project-URL: HomePage, https://github.com/postgrespro/testgres.os_ops
Keywords: testgres
Classifier: Intended Audience :: Developers
Classifier: Operating System :: Unix
Classifier: Programming Language :: Python :: 3 :: Only
Classifier: Programming Language :: Python :: 3.7
Classifier: Programming Language :: Python :: 3.8
Classifier: Programming Language :: Python :: 3.9
Classifier: Programming Language :: Python :: 3.10
Classifier: Programming Language :: Python :: 3.11
Classifier: Programming Language :: Python :: 3.12
Classifier: Programming Language :: Python :: 3.13
Classifier: Programming Language :: Python :: 3.14
Classifier: Topic :: Software Development :: Libraries
Classifier: Topic :: Software Development :: Testing
Requires-Python: >=3.7.17
License-File: LICENSE
Requires-Dist: psutil
Requires-Dist: six>=1.9.0
Requires-Dist: testgres.common<1.0.0,>=0.0.3
Dynamic: license-file
